frics/__about__.py
frics/__init__.py
frics/app.py
frics/codeshare.py
frics/frics.css
frics-1.0.0.dist-info/METADATA
frics-1.0.0.dist-info/WHEEL
frics-1.0.0.dist-info/entry_points.txt
frics-1.0.0.dist-info/licenses/LICENSE.txt
frics-1.0.0.dist-info/RECORD
